ComplimentForDopamine/__init__.py
ComplimentForDopamine/compliment.py
ComplimentForDopamine-1.0.0.dist-info/METADATA
ComplimentForDopamine-1.0.0.dist-info/WHEEL
ComplimentForDopamine-1.0.0.dist-info/top_level.txt
ComplimentForDopamine-1.0.0.dist-info/RECORD
