Metadata-Version: 2.1
Name: ComplimentForDopamine
Version: 1.0.0
Summary: A Python package that generates compliments for a given name
Home-page: UNKNOWN
Author: Evyatar Hazan
Author-email: 7127547@email.com
License: UNKNOWN
Platform: UNKNOWN
Classifier: Programming Language :: Python :: 3
Classifier: License :: OSI Approved :: MIT License
Classifier: Operating System :: OS Independent
Requires-Python: >=3.6
